{
  "completions": [
    {
      "created_at": 1601583790,
      "id": 448001,
      "lead_time": 13.878,
      "result": [
        {
          "from_name": "label",
          "id": "drlKNhh4n2",
          "image_rotation": 0,
          "original_height": 120,
          "original_width": 120,
          "parent_id": null,
          "source": "$image",
          "to_name": "image",
          "type": "polygonlabels",
          "value": {
            "points": [
              [
                20.666666666666668,
                42.833333333333336
              ],
              [
                25.666666666666668,
                46.666666666666664
              ],
              [
                27.666666666666668,
                44.666666666666664
              ],
              [
                28,
                44.166666666666664
              ],
              [
                35.333333333333336,
                48.666666666666664
              ],
              [
                39.5,
                50.666666666666664
              ],
              [
                48,
                52.333333333333336
              ],
              [
                53.166666666666664,
                51.166666666666664
              ],
              [
                59,
                53.333333333333336
              ],
              [
                63.166666666666664,
                54.666666666666664
              ],
              [
                63.666666666666664,
                50.166666666666664
              ],
              [
                57.333333333333336,
                48.666666666666664
              ],
              [
                55,
                44.333333333333336
              ],
              [
                51.5,
                39.333333333333336
              ],
              [
                42.666666666666664,
                42.333333333333336
              ],
              [
                34,
                39.833333333333336
              ],
              [
                28.5,
                41.833333333333336
              ],
              [
                23.666666666666668,
                40.166666666666664
              ]
            ],
            "polygonlabels": [
              "smoke"
            ]
          }
        }
      ]
    }
  ],
  "data": {
    "image": "http://localhost:8080/data/upload/5f7e7cdcf2c0853eb5e72fe7639a7ff9-10300_2019-09-26T10:16:47.221Z_23.png"
  },
  "id": 448
}