{
  "completions": [
    {
      "created_at": 1600954618,
      "id": 4622001,
      "lead_time": 23.512,
      "result": [
        {
          "from_name": "label",
          "id": "Mas0__sI_b",
          "image_rotation": 0,
          "original_height": 120,
          "original_width": 120,
          "parent_id": null,
          "source": "$image",
          "to_name": "image",
          "type": "polygonlabels",
          "value": {
            "points": [
              [
                77.33333333333333,
                49
              ],
              [
                73.66666666666667,
                38.666666666666664
              ],
              [
                80.66666666666667,
                39.166666666666664
              ],
              [
                83.16666666666667,
                34.5
              ],
              [
                87.66666666666667,
                38
              ],
              [
                94.16666666666667,
                46.166666666666664
              ],
              [
                95.66666666666667,
                46
              ],
              [
                98,
                39.5
              ],
              [
                99.5,
                35.5
              ],
              [
                99.5,
                0.3333333333333333
              ],
              [
                26,
                1
              ],
              [
                24.833333333333332,
                9.333333333333334
              ],
              [
                26.333333333333332,
                18.666666666666668
              ],
              [
                37.166666666666664,
                20.333333333333332
              ],
              [
                41.833333333333336,
                33
              ],
              [
                45.833333333333336,
                39.833333333333336
              ],
              [
                48.5,
                48.666666666666664
              ],
              [
                53.166666666666664,
                55
              ],
              [
                57.833333333333336,
                57.666666666666664
              ],
              [
                63,
                56.833333333333336
              ],
              [
                63.333333333333336,
                55.5
              ],
              [
                73,
                55.666666666666664
              ],
              [
                77.33333333333333,
                55.166666666666664
              ]
            ],
            "polygonlabels": [
              "smoke"
            ]
          }
        },
        {
          "from_name": "label",
          "id": "2OCJQexeMK",
          "image_rotation": 0,
          "original_height": 120,
          "original_width": 120,
          "parent_id": null,
          "source": "$image",
          "to_name": "image",
          "type": "polygonlabels",
          "value": {
            "points": [
              [
                38.166666666666664,
                99.33333333333333
              ],
              [
                30.5,
                93.5
              ],
              [
                21,
                73.5
              ],
              [
                14.833333333333334,
                77
              ],
              [
                7.666666666666667,
                70.83333333333333
              ],
              [
                5.5,
                62.833333333333336
              ],
              [
                6.666666666666667,
                54.833333333333336
              ],
              [
                1,
                50
              ],
              [
                1.1666666666666667,
                95
              ],
              [
                4.5,
                99.5
              ]
            ],
            "polygonlabels": [
              "smoke"
            ]
          }
        }
      ]
    }
  ],
  "data": {
    "image": "http://localhost:8080/data/upload/568b92f4d4a9e055fc0f8276ea1c66a0-44485_2019-12-04T10:46:43.886Z_16.png"
  },
  "id": 4622
}