{
  "completions": [
    {
      "created_at": 1600870051,
      "id": 4051001,
      "lead_time": 5.117,
      "result": [
        {
          "from_name": "label",
          "id": "Q_j7n2Ac-P",
          "image_rotation": 0,
          "original_height": 120,
          "original_width": 120,
          "parent_id": null,
          "source": "$image",
          "to_name": "image",
          "type": "polygonlabels",
          "value": {
            "points": [
              [
                40.5,
                57.166666666666664
              ],
              [
                44,
                53.666666666666664
              ],
              [
                47.333333333333336,
                52.333333333333336
              ],
              [
                47.333333333333336,
                49.666666666666664
              ],
              [
                44.166666666666664,
                46.5
              ],
              [
                39.833333333333336,
                47.333333333333336
              ],
              [
                38,
                49.166666666666664
              ],
              [
                38.833333333333336,
                54.666666666666664
              ],
              [
                38.166666666666664,
                57
              ]
            ],
            "polygonlabels": [
              "smoke"
            ]
          }
        }
      ]
    }
  ],
  "data": {
    "image": "http://localhost:8080/data/upload/2f266f5af1b1abecf4425d7ba80ae82a-6085_2019-04-30T09:43:05.284Z_7.png"
  },
  "id": 4051
}