{
  "completions": [
    {
      "created_at": 1600942025,
      "id": 4255001,
      "lead_time": 11.25,
      "result": [
        {
          "from_name": "label",
          "id": "u9gcUoyKG7",
          "image_rotation": 0,
          "original_height": 120,
          "original_width": 120,
          "parent_id": null,
          "source": "$image",
          "to_name": "image",
          "type": "polygonlabels",
          "value": {
            "points": [
              [
                51.833333333333336,
                49.166666666666664
              ],
              [
                48.166666666666664,
                44.833333333333336
              ],
              [
                43.5,
                39.166666666666664
              ],
              [
                37.666666666666664,
                31.833333333333332
              ],
              [
                38.500010172629516,
                36.999994913685235
              ],
              [
                43.666680230172695,
                43.5
              ],
              [
                47.166666666666664,
                48.333333333333336
              ],
              [
                50.666666666666664,
                51.333333333333336
              ]
            ],
            "polygonlabels": [
              "smoke"
            ]
          }
        }
      ]
    }
  ],
  "data": {
    "image": "http://localhost:8080/data/upload/551d929619549dd3a6609817cee76ac1-7199_2019-02-25T10:15:50.285Z_2.png"
  },
  "id": 4255
}